all_the_llms/__init__.py
all_the_llms/llm.py
all_the_llms/model_router.py
all_the_llms-0.1.10.dist-info/licenses/LICENSE
all_the_llms-0.1.10.dist-info/METADATA
all_the_llms-0.1.10.dist-info/WHEEL
all_the_llms-0.1.10.dist-info/top_level.txt
all_the_llms-0.1.10.dist-info/RECORD
